brain_atlas_toolkit/__init__.py
brain_atlas_toolkit/graph_tools.py
brain_atlas_toolkit-0.4.3.dist-info/LICENSE
brain_atlas_toolkit-0.4.3.dist-info/METADATA
brain_atlas_toolkit-0.4.3.dist-info/WHEEL
brain_atlas_toolkit-0.4.3.dist-info/top_level.txt
brain_atlas_toolkit-0.4.3.dist-info/RECORD
