Metadata-Version: 2.1
Name: brain-atlas-toolkit
Version: 0.4.3
Summary: A set of tools for navigating, viewing and manipulating hierarchical brain atlases
Home-page: https://github.com/BrainCOGS/brain_atlas_toolkit
Author: Austin Hoag
Author-email: austinthomashoag@gmail.com
License: UNKNOWN
Project-URL: Bug Tracker, https://github.com/BrainCOGS/brain_atlas_toolkit/issues
Platform: UNKNOWN
Classifier: Programming Language :: Python :: 3
Classifier: License :: OSI Approved :: MIT License
Classifier: Operating System :: OS Independent
Requires-Python: >=3.7
License-File: LICENSE
Requires-Dist: graphviz
